{
  "ok": true,
  "task": "ai_tracker",
  "mode": "latest_full",
  "channel": {
    "name": "Dwarkesh Patel",
    "tier": "tier1_kol_interview",
    "handle": "@dwarkeshpatel",
    "channel_id": null,
    "status": "active",
    "enabled": true,
    "resolved_channel_id": "UCXl4i9dYBrFOabk0xGmbkRA"
  },
  "date": "2026-04-04",
  "result": [
    {
      "id": "9-STuFQD9RY",
      "title": "Why Medieval Workers Didn't Need Government Safety Nets - Ada Palmer",
      "channel_title": "Dwarkesh Patel",
      "published_at": "2026-04-02T17:02:33Z",
      "description": "",
      "duration": "PT51S",
      "view_count": 69434,
      "like_count": 2516,
      "comment_count": 87,
      "url": "https://www.youtube.com/watch?v=9-STuFQD9RY"
    },
    {
      "id": "NvOn-o7g7A4",
      "title": "Machiavelli Chose Loyalty Over Power - Ada Palmer",
      "channel_title": "Dwarkesh Patel",
      "published_at": "2026-04-01T20:20:28Z",
      "description": "",
      "duration": "PT1M2S",
      "view_count": 133442,
      "like_count": 3101,
      "comment_count": 61,
      "url": "https://www.youtube.com/watch?v=NvOn-o7g7A4"
    },
    {
      "id": "x21Sac_RnyE",
      "title": "Huawei Was About to Beat NVIDIA - Dylan Patel",
      "channel_title": "Dwarkesh Patel",
      "published_at": "2026-03-31T17:54:45Z",
      "description": "",
      "duration": "PT38S",
      "view_count": 25762,
      "like_count": 411,
      "comment_count": 88,
      "url": "https://www.youtube.com/watch?v=x21Sac_RnyE"
    },
    {
      "id": "fRpynA_dYtc",
      "title": "How AI Is Killing Cheap Smartphones - Dylan Patel",
      "channel_title": "Dwarkesh Patel",
      "published_at": "2026-03-30T19:55:21Z",
      "description": "",
      "duration": "PT1M1S",
      "view_count": 50376,
      "like_count": 714,
      "comment_count": 35,
      "url": "https://www.youtube.com/watch?v=fRpynA_dYtc"
    },
    {
      "id": "i9-0Iowgtu4",
      "title": "Why Great Thinking Needs Distraction - Terence Tao",
      "channel_title": "Dwarkesh Patel",
      "published_at": "2026-03-29T19:13:06Z",
      "description": "",
      "duration": "PT1M27S",
      "view_count": 57791,
      "like_count": 2453,
      "comment_count": 58,
      "url": "https://www.youtube.com/watch?v=i9-0Iowgtu4"
    }
  ],
  "error": null,
  "meta": {
    "generated_at": "2026-04-03T17:00:38Z",
    "count": 5
  }
}